{"GlobalPropertiesHash":"SagXM3PLPw5jtcCTGKeUl5OtnxQt3tALQS7BvZqf2L8=","FingerprintPatternsHash":"gq3WsqcKBUGTSNle7RKKyXRIwh7M8ccEqOqYvIzoM04=","PropertyOverridesHash":"8ZRc1sGeVrPBx4lD717BgRaQekyh78QKV9SKsdt638U=","InputHashes":["1dEcRY/rZ\u002BB3HdMEnBPffSOAMCLbvQRsrzhFJfqMsd8=","R7YW1yV0tKGCPm7DfnkQ/BNS0hfNSPWP\u002B7eZXz6v\u002B2M=","adjmaJ5wqx8BR3NKARq35BpZBq2Yr/HOwuHVh/y/cwg=","nSJlPRsrmxCOfBUSDZ6MLDsTF\u002BMfbTM60sfJtnIjEt4=","1oaC4i0gD3Ws7R56I8xlPSFUU549tlm3f0OJnNM6exc=","OsYXML5bj5\u002BAP2W6IOvG0JnEkYDaA1CP2APjc7Fq4hY=","62IguZvEQcxBJVAvPmmxXiqmPuz7Y11\u002BAtv6N5lkRrs=","/PSaDLCxe\u002ByEaAyOKW0rupvnRWUQDT9Ckb5F/QrJytg=","qXi65OlmU3Ln5r9BNO8umSPTmYlmrj0xqlpLhl41i\u002Bs=","G/SppmE6NTf73SAnje6Z5iDq1Xka0x4OXfMbo8r/FaQ=","VK2Hj9DRDnFJ0Ovmn8UAGzM7/jmM1x8cCeiJYdfzFaE=","aLAC0H\u002Bu/4JmGmIJeCBe4loI\u002Brktb4PDGTvtTau1Prs=","bncF\u002Bd4vJ47qENMiAOXbwLedqFTQlC9rFq0jFN0lqc0=","Qf3Uy9K/R5/BzbJckaY\u002B8qiDNvL8YPtPpmmNpFVsObs=","fsTOaxX7wXyJ0VkPit7DVeTlu6SN/\u002B1Yezdry0jHi9I="],"CachedAssets":{"VK2Hj9DRDnFJ0Ovmn8UAGzM7/jmM1x8cCeiJYdfzFaE=":{"Identity":"C:\\Users\\admin\\TodoApi\\TodoApi\\wwwroot\\uploads\\1\\Nour El Houda Akhdari.pdf","SourceId":"TodoApi","SourceType":"Discovered","ContentRoot":"C:\\Users\\admin\\TodoApi\\TodoApi\\wwwroot\\","BasePath":"_content/TodoApi","RelativePath":"uploads/1/Nour El Houda Akhdari#[.{fingerprint}]?.pdf","AssetKind":"All","AssetMode":"All","AssetRole":"Primary","AssetMergeBehavior":null,"AssetMergeSource":"","RelatedAsset":null,"AssetTraitName":null,"AssetTraitValue":null,"Fingerprint":"m5c7yh0qav","Integrity":"Sv85twYCWpcFxOpIsjDzTRonOGspWENDu0n0112EnP4=","CopyToOutputDirectory":"Never","CopyToPublishDirectory":"PreserveNewest","OriginalItemSpec":"wwwroot\\uploads\\1\\Nour El Houda Akhdari.pdf","FileLength":654606,"LastWriteTime":"2025-07-20T14:40:21.3012393+00:00"},"/PSaDLCxe\u002ByEaAyOKW0rupvnRWUQDT9Ckb5F/QrJytg=":{"Identity":"C:\\Users\\admin\\TodoApi\\TodoApi\\wwwroot\\uploads\\1\\export_subscriptions.xlsx","SourceId":"TodoApi","SourceType":"Discovered","ContentRoot":"C:\\Users\\admin\\TodoApi\\TodoApi\\wwwroot\\","BasePath":"_content/TodoApi","RelativePath":"uploads/1/export_subscriptions#[.{fingerprint}]?.xlsx","AssetKind":"All","AssetMode":"All","AssetRole":"Primary","AssetMergeBehavior":null,"AssetMergeSource":"","RelatedAsset":null,"AssetTraitName":null,"AssetTraitValue":null,"Fingerprint":"doe7uxwz4i","Integrity":"8/cJ8DKpH/euHOXLr5mJJxJfdW/gZWtfRilK0ul/txQ=","CopyToOutputDirectory":"Never","CopyToPublishDirectory":"PreserveNewest","OriginalItemSpec":"wwwroot\\uploads\\1\\export_subscriptions.xlsx","FileLength":5502,"LastWriteTime":"2025-07-27T14:54:15.8099086+00:00"},"R7YW1yV0tKGCPm7DfnkQ/BNS0hfNSPWP\u002B7eZXz6v\u002B2M=":{"Identity":"C:\\Users\\admin\\TodoApi\\TodoApi\\wwwroot\\uploads\\1\\116fa68aa27896a49a27cf9823379924.jpg","SourceId":"TodoApi","SourceType":"Discovered","ContentRoot":"C:\\Users\\admin\\TodoApi\\TodoApi\\wwwroot\\","BasePath":"_content/TodoApi","RelativePath":"uploads/1/116fa68aa27896a49a27cf9823379924#[.{fingerprint}]?.jpg","AssetKind":"All","AssetMode":"All","AssetRole":"Primary","AssetMergeBehavior":null,"AssetMergeSource":"","RelatedAsset":null,"AssetTraitName":null,"AssetTraitValue":null,"Fingerprint":"wizc8dam50","Integrity":"KEXqn0W2yCn32WJ8XNGdEPWy1\u002BaG/t\u002B2YdN1sFk0rpg=","CopyToOutputDirectory":"Never","CopyToPublishDirectory":"PreserveNewest","OriginalItemSpec":"wwwroot\\uploads\\1\\116fa68aa27896a49a27cf9823379924.jpg","FileLength":24491,"LastWriteTime":"2025-07-29T14:57:19.4258337+00:00"},"adjmaJ5wqx8BR3NKARq35BpZBq2Yr/HOwuHVh/y/cwg=":{"Identity":"C:\\Users\\admin\\TodoApi\\TodoApi\\wwwroot\\uploads\\1\\4442cfadfd97b733b79d36036b07335d.jpg","SourceId":"TodoApi","SourceType":"Discovered","ContentRoot":"C:\\Users\\admin\\TodoApi\\TodoApi\\wwwroot\\","BasePath":"_content/TodoApi","RelativePath":"uploads/1/4442cfadfd97b733b79d36036b07335d#[.{fingerprint}]?.jpg","AssetKind":"All","AssetMode":"All","AssetRole":"Primary","AssetMergeBehavior":null,"AssetMergeSource":"","RelatedAsset":null,"AssetTraitName":null,"AssetTraitValue":null,"Fingerprint":"ocny6kjrke","Integrity":"SM89dKDH\u002BD3\u002BDFHX1D0QzTlu67lbNCiwOWGSq4Pi9cE=","CopyToOutputDirectory":"Never","CopyToPublishDirectory":"PreserveNewest","OriginalItemSpec":"wwwroot\\uploads\\1\\4442cfadfd97b733b79d36036b07335d.jpg","FileLength":11658,"LastWriteTime":"2025-07-29T14:57:19.418205+00:00"},"nSJlPRsrmxCOfBUSDZ6MLDsTF\u002BMfbTM60sfJtnIjEt4=":{"Identity":"C:\\Users\\admin\\TodoApi\\TodoApi\\wwwroot\\uploads\\1\\8f192278543c94cacb1cb19bfab6b2df.jpg","SourceId":"TodoApi","SourceType":"Discovered","ContentRoot":"C:\\Users\\admin\\TodoApi\\TodoApi\\wwwroot\\","BasePath":"_content/TodoApi","RelativePath":"uploads/1/8f192278543c94cacb1cb19bfab6b2df#[.{fingerprint}]?.jpg","AssetKind":"All","AssetMode":"All","AssetRole":"Primary","AssetMergeBehavior":null,"AssetMergeSource":"","RelatedAsset":null,"AssetTraitName":null,"AssetTraitValue":null,"Fingerprint":"ofnrvy3e4j","Integrity":"ZKbchZrQz2VkjyVZvAQwGrMxvL05sEVH2tUWqtZik8E=","CopyToOutputDirectory":"Never","CopyToPublishDirectory":"PreserveNewest","OriginalItemSpec":"wwwroot\\uploads\\1\\8f192278543c94cacb1cb19bfab6b2df.jpg","FileLength":37286,"LastWriteTime":"2025-07-29T14:57:19.4298444+00:00"},"1oaC4i0gD3Ws7R56I8xlPSFUU549tlm3f0OJnNM6exc=":{"Identity":"C:\\Users\\admin\\TodoApi\\TodoApi\\wwwroot\\uploads\\1\\app_pictures_1649855739.jpg","SourceId":"TodoApi","SourceType":"Discovered","ContentRoot":"C:\\Users\\admin\\TodoApi\\TodoApi\\wwwroot\\","BasePath":"_content/TodoApi","RelativePath":"uploads/1/app_pictures_1649855739#[.{fingerprint}]?.jpg","AssetKind":"All","AssetMode":"All","AssetRole":"Primary","AssetMergeBehavior":null,"AssetMergeSource":"","RelatedAsset":null,"AssetTraitName":null,"AssetTraitValue":null,"Fingerprint":"yl1cpcp6o1","Integrity":"2vMcMau46c\u002BD48EJDyCo/PBawaeR6NmBVrXgWg\u002BKKAY=","CopyToOutputDirectory":"Never","CopyToPublishDirectory":"PreserveNewest","OriginalItemSpec":"wwwroot\\uploads\\1\\app_pictures_1649855739.jpg","FileLength":76801,"LastWriteTime":"2025-07-29T14:03:49.8484245+00:00"},"OsYXML5bj5\u002BAP2W6IOvG0JnEkYDaA1CP2APjc7Fq4hY=":{"Identity":"C:\\Users\\admin\\TodoApi\\TodoApi\\wwwroot\\uploads\\1\\avatar.png","SourceId":"TodoApi","SourceType":"Discovered","ContentRoot":"C:\\Users\\admin\\TodoApi\\TodoApi\\wwwroot\\","BasePath":"_content/TodoApi","RelativePath":"uploads/1/avatar#[.{fingerprint}]?.png","AssetKind":"All","AssetMode":"All","AssetRole":"Primary","AssetMergeBehavior":null,"AssetMergeSource":"","RelatedAsset":null,"AssetTraitName":null,"AssetTraitValue":null,"Fingerprint":"cf1dip6etn","Integrity":"eH47vZ6iz/Z3FZc6RNO5X32VLFzOYkyVdoJcRuxUwBY=","CopyToOutputDirectory":"Never","CopyToPublishDirectory":"PreserveNewest","OriginalItemSpec":"wwwroot\\uploads\\1\\avatar.png","FileLength":251956,"LastWriteTime":"2025-07-29T14:25:03.4226308+00:00"},"62IguZvEQcxBJVAvPmmxXiqmPuz7Y11\u002BAtv6N5lkRrs=":{"Identity":"C:\\Users\\admin\\TodoApi\\TodoApi\\wwwroot\\uploads\\1\\Copy of CV of Rayane ATOUI.pdf (1).pdf","SourceId":"TodoApi","SourceType":"Discovered","ContentRoot":"C:\\Users\\admin\\TodoApi\\TodoApi\\wwwroot\\","BasePath":"_content/TodoApi","RelativePath":"uploads/1/Copy of CV of Rayane ATOUI.pdf (1)#[.{fingerprint}]?.pdf","AssetKind":"All","AssetMode":"All","AssetRole":"Primary","AssetMergeBehavior":null,"AssetMergeSource":"","RelatedAsset":null,"AssetTraitName":null,"AssetTraitValue":null,"Fingerprint":"idxbdi0kxn","Integrity":"Ss2AjXUzAEiVsgzQoANj7rDK\u002BK/I8XlYA\u002B9MZfHlfjg=","CopyToOutputDirectory":"Never","CopyToPublishDirectory":"PreserveNewest","OriginalItemSpec":"wwwroot\\uploads\\1\\Copy of CV of Rayane ATOUI.pdf (1).pdf","FileLength":94709,"LastWriteTime":"2025-07-29T14:07:51.9780235+00:00"},"qXi65OlmU3Ln5r9BNO8umSPTmYlmrj0xqlpLhl41i\u002Bs=":{"Identity":"C:\\Users\\admin\\TodoApi\\TodoApi\\wwwroot\\uploads\\1\\Markdown to PDF (1).pdf","SourceId":"TodoApi","SourceType":"Discovered","ContentRoot":"C:\\Users\\admin\\TodoApi\\TodoApi\\wwwroot\\","BasePath":"_content/TodoApi","RelativePath":"uploads/1/Markdown to PDF (1)#[.{fingerprint}]?.pdf","AssetKind":"All","AssetMode":"All","AssetRole":"Primary","AssetMergeBehavior":null,"AssetMergeSource":"","RelatedAsset":null,"AssetTraitName":null,"AssetTraitValue":null,"Fingerprint":"wdly4mfn8h","Integrity":"PBMBSDby1u2u2kX2JOiYH1iMlSRZFrGXyU7jwyl0uFM=","CopyToOutputDirectory":"Never","CopyToPublishDirectory":"PreserveNewest","OriginalItemSpec":"wwwroot\\uploads\\1\\Markdown to PDF (1).pdf","FileLength":18215,"LastWriteTime":"2025-07-29T14:07:51.972035+00:00"},"G/SppmE6NTf73SAnje6Z5iDq1Xka0x4OXfMbo8r/FaQ=":{"Identity":"C:\\Users\\admin\\TodoApi\\TodoApi\\wwwroot\\uploads\\1\\Markdown to PDF.pdf","SourceId":"TodoApi","SourceType":"Discovered","ContentRoot":"C:\\Users\\admin\\TodoApi\\TodoApi\\wwwroot\\","BasePath":"_content/TodoApi","RelativePath":"uploads/1/Markdown to PDF#[.{fingerprint}]?.pdf","AssetKind":"All","AssetMode":"All","AssetRole":"Primary","AssetMergeBehavior":null,"AssetMergeSource":"","RelatedAsset":null,"AssetTraitName":null,"AssetTraitValue":null,"Fingerprint":"x4tpap25xj","Integrity":"P/LAf1KgJNyRD75MpU62GacSJrYM18hG3dv8yf0Or2Y=","CopyToOutputDirectory":"Never","CopyToPublishDirectory":"PreserveNewest","OriginalItemSpec":"wwwroot\\uploads\\1\\Markdown to PDF.pdf","FileLength":37273,"LastWriteTime":"2025-07-29T13:52:51.6657311+00:00"},"aLAC0H\u002Bu/4JmGmIJeCBe4loI\u002Brktb4PDGTvtTau1Prs=":{"Identity":"C:\\Users\\admin\\TodoApi\\TodoApi\\wwwroot\\uploads\\1\\Themes.pdf","SourceId":"TodoApi","SourceType":"Discovered","ContentRoot":"C:\\Users\\admin\\TodoApi\\TodoApi\\wwwroot\\","BasePath":"_content/TodoApi","RelativePath":"uploads/1/Themes#[.{fingerprint}]?.pdf","AssetKind":"All","AssetMode":"All","AssetRole":"Primary","AssetMergeBehavior":null,"AssetMergeSource":"","RelatedAsset":null,"AssetTraitName":null,"AssetTraitValue":null,"Fingerprint":"tdpcq3jpzm","Integrity":"fz4vnPuTSdPaGURrvf4mnS11Pr\u002Brd7S8t7wElYAH6/o=","CopyToOutputDirectory":"Never","CopyToPublishDirectory":"PreserveNewest","OriginalItemSpec":"wwwroot\\uploads\\1\\Themes.pdf","FileLength":68415,"LastWriteTime":"2025-07-29T14:58:28.5229926+00:00"},"1dEcRY/rZ\u002BB3HdMEnBPffSOAMCLbvQRsrzhFJfqMsd8=":{"Identity":"C:\\Users\\admin\\TodoApi\\TodoApi\\wwwroot\\uploads\\1\\1000002936.jpg","SourceId":"TodoApi","SourceType":"Discovered","ContentRoot":"C:\\Users\\admin\\TodoApi\\TodoApi\\wwwroot\\","BasePath":"_content/TodoApi","RelativePath":"uploads/1/1000002936#[.{fingerprint}]?.jpg","AssetKind":"All","AssetMode":"All","AssetRole":"Primary","AssetMergeBehavior":null,"AssetMergeSource":"","RelatedAsset":null,"AssetTraitName":null,"AssetTraitValue":null,"Fingerprint":"jwg9yopy0x","Integrity":"04\u002BOt5CbpuMisYS6uJln/RTbGQhl\u002BGKK3C\u002BpJUQiqU0=","CopyToOutputDirectory":"Never","CopyToPublishDirectory":"PreserveNewest","OriginalItemSpec":"wwwroot\\uploads\\1\\1000002936.jpg","FileLength":219472,"LastWriteTime":"2025-07-29T14:59:03.6256043+00:00"},"bncF\u002Bd4vJ47qENMiAOXbwLedqFTQlC9rFq0jFN0lqc0=":{"Identity":"C:\\Users\\admin\\TodoApi\\TodoApi\\wwwroot\\uploads\\1\\ukran.jpg","SourceId":"TodoApi","SourceType":"Discovered","ContentRoot":"C:\\Users\\admin\\TodoApi\\TodoApi\\wwwroot\\","BasePath":"_content/TodoApi","RelativePath":"uploads/1/ukran#[.{fingerprint}]?.jpg","AssetKind":"All","AssetMode":"All","AssetRole":"Primary","AssetMergeBehavior":null,"AssetMergeSource":"","RelatedAsset":null,"AssetTraitName":null,"AssetTraitValue":null,"Fingerprint":"jvrfjtv8hm","Integrity":"IU47d3N8GeXxtI/sTUEnRjibcSnmvAwZ1/f1UQETJFE=","CopyToOutputDirectory":"Never","CopyToPublishDirectory":"PreserveNewest","OriginalItemSpec":"wwwroot\\uploads\\1\\ukran.jpg","FileLength":240431,"LastWriteTime":"2025-07-29T15:00:51.9518172+00:00"}},"CachedCopyCandidates":{}}